fafreplay/__init__.py
fafreplay/_fafreplay.pypy38-pp73-win_amd64.pyd
faf_replay_parser-0.6.0.dist-info/LICENSE
faf_replay_parser-0.6.0.dist-info/METADATA
faf_replay_parser-0.6.0.dist-info/WHEEL
faf_replay_parser-0.6.0.dist-info/top_level.txt
faf_replay_parser-0.6.0.dist-info/RECORD
