Metadata-Version: 2.1
Name: faf-replay-parser
Version: 0.6.0
Summary: Python bindings for faf-replay-parser
Home-page: https://github.com/Askaholic/faf-replay-parser-python
Author: Askaholic
License: License :: OSI Approved :: GNU Lesser General Public License v3 (LGPLv3)
Project-URL: Source, https://github.com/Askaholic/faf-replay-parser-python
Project-URL: Tracker, https://github.com/Askaholic/faf-replay-parser-python/issues
Platform: any
Classifier: Development Status :: 3 - Alpha
Classifier: License :: OSI Approved :: GNU Lesser General Public License v3 (LGPLv3)
Classifier: Programming Language :: Python :: 3.8
Classifier: Programming Language :: Python :: 3.9
Classifier: Programming Language :: Python :: 3.10
Classifier: Programming Language :: Python :: 3.11
Classifier: Programming Language :: Python :: 3.12
Classifier: Operating System :: POSIX :: Linux
Classifier: Operating System :: Microsoft :: Windows
Classifier: Operating System :: MacOS
Classifier: Topic :: Games/Entertainment :: Real Time Strategy
Requires-Python: >=3.8
License-File: LICENSE
Provides-Extra: faf
Requires-Dist: zstd>=1.1; extra == "faf"
